{
	"archive" : {},
	"artifacts" : 
	[
		{
			"path" : "libdgfem.a"
		}
	],
	"backtrace" : 1,
	"backtraceGraph" : 
	{
		"commands" : 
		[
			"add_library",
			"target_include_directories"
		],
		"files" : 
		[
			"CMakeLists.txt"
		],
		"nodes" : 
		[
			{
				"file" : 0
			},
			{
				"command" : 0,
				"file" : 0,
				"line" : 7,
				"parent" : 0
			},
			{
				"command" : 1,
				"file" : 0,
				"line" : 8,
				"parent" : 0
			}
		]
	},
	"compileGroups" : 
	[
		{
			"compileCommandFragments" : 
			[
				{
					"fragment" : "-g"
				}
			],
			"includes" : 
			[
				{
					"backtrace" : 2,
					"path" : "/home/mauro/workspace/university/Master_Thesis_2025/cpp/include"
				},
				{
					"backtrace" : 2,
					"path" : "/home/mauro/workspace/university/Master_Thesis_2025/cpp/third_party"
				}
			],
			"language" : "CXX",
			"sourceIndexes" : 
			[
				0
			]
		}
	],
	"id" : "dgfem::@6890427a1f51a3e7e1df",
	"name" : "dgfem",
	"nameOnDisk" : "libdgfem.a",
	"paths" : 
	{
		"build" : ".",
		"source" : "."
	},
	"sourceGroups" : 
	[
		{
			"name" : "Source Files",
			"sourceIndexes" : 
			[
				0
			]
		}
	],
	"sources" : 
	[
		{
			"backtrace" : 1,
			"compileGroupIndex" : 0,
			"path" : "src/fem/stiffness_matrix_1d.cpp",
			"sourceGroupIndex" : 0
		}
	],
	"type" : "STATIC_LIBRARY"
}
